ansicolor/__init__.py
ansicolor/ansicolor.py
ansicolor/demos.py
ansicolor-0.3.3.dist-info/licenses/LICENSE
tests/__init__.py
tests/test_colors.py
tests/test_imports.py
ansicolor-0.3.3.dist-info/METADATA
ansicolor-0.3.3.dist-info/WHEEL
ansicolor-0.3.3.dist-info/top_level.txt
ansicolor-0.3.3.dist-info/RECORD
