Metadata-Version: 2.4
Name: ansicolor
Version: 0.3.3
Summary: A library to produce ansi color output and colored highlighting and diffing
Home-page: https://github.com/numerodix/ansicolor
Author: Martin Matusiak
Author-email: numerodix@gmail.com
Classifier: License :: OSI Approved :: Apache Software License
Classifier: Programming Language :: Python :: 2.7
Classifier: Programming Language :: Python :: 3
Classifier: Programming Language :: Python :: 3.8
Classifier: Programming Language :: Python :: 3.9
Classifier: Programming Language :: Python :: Implementation :: CPython
License-File: LICENSE
Dynamic: author
Dynamic: author-email
Dynamic: classifier
Dynamic: home-page
Dynamic: license-file
Dynamic: summary
